{
    "version": "0.14.0",
    "architecture": {
        "32bit": {
            "url": "https://github.com/signcl/bayes-releases/releases/download/v0.14.0/bayes_windows_386.zip",
            "bin": [
                "bayes.exe"
            ],
            "hash": "915a465f291e0dbba597f39ea6e0baa070e41550c4862e432f4a05bfa75be59f"
        },
        "64bit": {
            "url": "https://github.com/signcl/bayes-releases/releases/download/v0.14.0/bayes_windows_amd64.zip",
            "bin": [
                "bayes.exe"
            ],
            "hash": "449761191d8394a95a33aab320ff13463d98b250c4b236ac2fd20188da6c22d4"
        }
    },
    "homepage": "https://openbayes.com",
    "license": "MIT",
    "description": "CLI command-line tools for OpenBayes console"
}